carpicommons/__init__.py
carpicommons/errors.py
carpicommons/log.py
carpi_commons-0.1.1.dist-info/LICENSE
carpi_commons-0.1.1.dist-info/METADATA
carpi_commons-0.1.1.dist-info/WHEEL
carpi_commons-0.1.1.dist-info/top_level.txt
carpi_commons-0.1.1.dist-info/RECORD
